crewai/__init__.py
crewai/agent.py
crewai/agents/__init__.py
crewai/agents/cache/__init__.py
crewai/agents/cache/cache_handler.py
crewai/agents/executor.py
crewai/agents/parser.py
crewai/agents/tools_handler.py
crewai/cli/__init__.py
crewai/cli/cli.py
crewai/cli/create_crew.py
crewai/cli/templates/.gitignore
crewai/cli/templates/README.md
crewai/cli/templates/__init__.py
crewai/cli/templates/config/agents.yaml
crewai/cli/templates/config/tasks.yaml
crewai/cli/templates/crew.py
crewai/cli/templates/main.py
crewai/cli/templates/pyproject.toml
crewai/cli/templates/tools/__init__.py
crewai/cli/templates/tools/custom_tool.py
crewai/crew.py
crewai/process.py
crewai/project/__init__.py
crewai/project/annotations.py
crewai/project/crew_base.py
crewai/task.py
crewai/tasks/__init__.py
crewai/tasks/task_output.py
crewai/telemetry/__init__.py
crewai/telemetry/telemetry.py
crewai/tools/__init__.py
crewai/tools/agent_tools.py
crewai/tools/cache_tools.py
crewai/tools/tool_calling.py
crewai/tools/tool_output_parser.py
crewai/tools/tool_usage.py
crewai/translations/el.json
crewai/translations/en.json
crewai/utilities/__init__.py
crewai/utilities/converter.py
crewai/utilities/crew_pydantic_output_parser.py
crewai/utilities/i18n.py
crewai/utilities/instructor.py
crewai/utilities/logger.py
crewai/utilities/printer.py
crewai/utilities/prompts.py
crewai/utilities/pydantic_schema_parser.py
crewai/utilities/rpm_controller.py
crewai/utilities/token_counter_callback.py
crewai_clean-0.22.5.dist-info/LICENSE
crewai_clean-0.22.5.dist-info/METADATA
crewai_clean-0.22.5.dist-info/WHEEL
crewai_clean-0.22.5.dist-info/entry_points.txt
crewai_clean-0.22.5.dist-info/RECORD
