Metadata-Version: 2.1
Name: crewai-clean
Version: 0.22.5
Summary: Cutting-edge framework for orchestrating role-playing, autonomous AI agents. By fostering collaborative intelligence, CrewAI empowers agents to work together seamlessly, tackling complex tasks.
Author: Joao Moura
Author-email: joao@crewai.com
Requires-Python: >=3.10,<=3.13
Classifier: Programming Language :: Python :: 3
Classifier: Programming Language :: Python :: 3.10
Classifier: Programming Language :: Python :: 3.11
Classifier: Programming Language :: Python :: 3.12
Provides-Extra: tools
Requires-Dist: click (>=8.1.7,<9.0.0)
Requires-Dist: crewai-tools (>=0.0.15,<0.0.16) ; extra == "tools"
Requires-Dist: instructor (>=0.5.2,<0.6.0)
Requires-Dist: langchain (>=0.1.10,<0.2.0)
Requires-Dist: langchain-openai (>=0.0.5,<0.0.6)
Requires-Dist: openai (>=1.13.3,<2.0.0)
Requires-Dist: opentelemetry-api (>=1.22.0,<2.0.0)
Requires-Dist: opentelemetry-exporter-otlp-proto-http (>=1.22.0,<2.0.0)
Requires-Dist: opentelemetry-sdk (>=1.22.0,<2.0.0)
Requires-Dist: pydantic (>=2.4.2,<3.0.0)
Requires-Dist: python-dotenv (==1.0.0)
Requires-Dist: regex (>=2023.12.25,<2024.0.0)
Project-URL: Documentation, https://github.com/joaomdmoura/CrewAI/wiki/Index
Project-URL: Homepage, https://crewai.com
Project-URL: Repository, https://github.com/joaomdmoura/crewai
